indico_topmenu_extender/__init__.py
indico_topmenu_extender/plugin.py
indico_topmenu_extender/version.py
indico_plugin_topmenuextender-3.0.1.dist-info/LICENSE
indico_plugin_topmenuextender-3.0.1.dist-info/METADATA
indico_plugin_topmenuextender-3.0.1.dist-info/WHEEL
indico_plugin_topmenuextender-3.0.1.dist-info/entry_points.txt
indico_plugin_topmenuextender-3.0.1.dist-info/top_level.txt
indico_plugin_topmenuextender-3.0.1.dist-info/RECORD
